pyAPNsKit/APNsBody.py
pyAPNsKit/APNsHeader.py
pyAPNsKit/__init__.py
pyAPNsKit/apns.py
pyAPNsKit/helper.py
pyAPNsKit/types.py
pyapnskit-0.1.3.dist-info/licenses/LICENSE
pyapnskit-0.1.3.dist-info/METADATA
pyapnskit-0.1.3.dist-info/WHEEL
pyapnskit-0.1.3.dist-info/top_level.txt
pyapnskit-0.1.3.dist-info/RECORD
